ink_extensions/__init__.py
ink_extensions/bezmisc.py
ink_extensions/cspsubdiv.py
ink_extensions/cubicsuperpath.py
ink_extensions/ffgeom.py
ink_extensions/ffgeom_legacy.py
ink_extensions/inkex.py
ink_extensions/simplepath.py
ink_extensions/simplestyle.py
ink_extensions/simpletransform.py
ink_extensions_utils/__init__.py
ink_extensions_utils/exit_status.py
ink_extensions_utils/message.py
ink_extensions-2.1.0.dist-info/LICENSE
ink_extensions-2.1.0.dist-info/METADATA
ink_extensions-2.1.0.dist-info/WHEEL
ink_extensions-2.1.0.dist-info/top_level.txt
ink_extensions-2.1.0.dist-info/RECORD
