Metadata-Version: 2.1
Name: ink_extensions
Version: 2.1.0
Home-page: https://github.com/evil-mad/ink_extensions
License-File: LICENSE
Requires-Dist: lxml
Provides-Extra: dev
Requires-Dist: coverage; extra == "dev"
Provides-Extra: test
Requires-Dist: mock; extra == "test"
